qurix/__init__.py
qurix/data/__init__.py
qurix/data/catalog/__init__.py
qurix/data/catalog/__version__.py
qurix/data/catalog/client.py
qurix/data/catalog/dataloader.py
qurix/data/catalog/entities.py
qurix/data/catalog/exceptions.py
qurix/data/catalog/utils.py
tests/__init__.py
tests/test_client.py
tests/test_dataloader.py
tests/test_entities.py
tests/utils.py
tests_integration/__init__.py
tests_integration/test_client_db2.py
tests_integration/test_client_pg.py
tests_integration/scripts/prepare_sql.py
tests_integration/scripts_db2/prepare_sql.py
qurix_data_catalog-1.11.3.dist-info/METADATA
qurix_data_catalog-1.11.3.dist-info/WHEEL
qurix_data_catalog-1.11.3.dist-info/top_level.txt
qurix_data_catalog-1.11.3.dist-info/RECORD
