Metadata-Version: 2.1
Name: qurix-data-catalog
Version: 1.11.3
Summary: qurix Data catalog client for Python
Home-page: https://github.com/qurixtechnology/qurix-data-catalog
Author: qurix Technology GmbH
Keywords: python
Requires-Python: >=3.10, <4
Requires-Dist: Cython
Requires-Dist: pandas
Requires-Dist: annotated-types ==0.5.0
Requires-Dist: autopep8 ==2.0.2
Requires-Dist: connectorx ==0.3.2
Requires-Dist: et-xmlfile ==1.1.0
Requires-Dist: iniconfig ==2.0.0
Requires-Dist: numpy ==1.25.2
Requires-Dist: openpyxl ==3.1.2
Requires-Dist: packaging ==23.1
Requires-Dist: pluggy ==1.2.0
Requires-Dist: pyarrow ==12.0.1
Requires-Dist: pycodestyle ==2.11.0
Requires-Dist: pydantic ==2.1.1
Requires-Dist: pydantic-core ==2.4.0
Requires-Dist: pytest ==7.4.0
Requires-Dist: python-dateutil ==2.8.2
Requires-Dist: pytz ==2023.3
Requires-Dist: six ==1.16.0
Requires-Dist: typing-extensions ==4.7.1
Requires-Dist: tzdata ==2023.3
Requires-Dist: XlsxWriter
Requires-Dist: python-dotenv
Requires-Dist: sqlalchemy
Requires-Dist: ibm-db-sa
Requires-Dist: psycopg2-binary
Provides-Extra: dev
Requires-Dist: pytest ==7.3.1 ; extra == 'dev'
Requires-Dist: flake8 ==6.0.0 ; extra == 'dev'
Requires-Dist: pytest-flake8 ==1.1.1 ; extra == 'dev'
Requires-Dist: pytest-cov ==4.0.0 ; extra == 'dev'
Requires-Dist: wheel ==0.40.0 ; extra == 'dev'
Requires-Dist: twine ==4.0.2 ; extra == 'dev'
